{
    "_id": "66f4403288c998ad9aa31d19",
    "name": "Coffee Machine Service",
    "category": "vehicle-service",
    "thumbnail": "https://upload.digitalauto.tech/data/store-be/35658f86-f611-43a4-b2f8-8b2fe778fc40.jpeg",
    "images": [],
    "video": "none",
    "shortDesc": "Service to enable coffee machine on vehicle",
    "fullDesc": "Service to enable coffee machine on vehicle",
    "visibility": "private",
    "authors": ["Dev"],
    "deleted": false,
    "createdBy": "6555b2c98edc2aa75824b4df",
    "likes": [],
    "downloads": 0,
    "entryPoint": "NAN",
    "dashboardConfig": {
        "DockerImageURL": "phongbosch/dk_service_coffee:latest",
        "ExecutionCommand": "python run_script.py",
        "ExecutionFileURL": "https://example.com/script.py",
        "ExecutionFileType": "Python",
        "SignalList": [
            {
                "vss_api": "Vehicle.BYOD.CoffeeMachine.Brew",
                "vss_type": "actuator",
                "datatype": "boolean",
                "description": "",
                "vss2dbc_signal": "",
                "dbc2vss_signal": ""
            },
            {
                "vss_api": "Vehicle.BYOD.CoffeeMachine.IsStarted",
                "vss_type": "sensor",
                "datatype": "boolean",
                "description": "",
                "vss2dbc_signal": "",
                "dbc2vss_signal": ""
            }
        ],
        "RuntimeCfg": {
            "address": "f7:c3:cb:6d:35:55"
        }

    },
    "state": "approved",
    "source": "",
    "type": "",
    "createdAt": "2024-09-25T16:54:10.759Z",
    "updatedAt": "2024-09-26T09:46:19.589Z",
    "modelId": "",
    "rating": null,
    "ratingCount": 0,
    "userLike": false
}
